paizhaojieti_stdio_mcp-1.0.0.dist-info/licenses/LICENSE
paizhaojieti_stdio_mcp_package/__init__.py
paizhaojieti_stdio_mcp_package/server.py
paizhaojieti_stdio_mcp-1.0.0.dist-info/METADATA
paizhaojieti_stdio_mcp-1.0.0.dist-info/WHEEL
paizhaojieti_stdio_mcp-1.0.0.dist-info/entry_points.txt
paizhaojieti_stdio_mcp-1.0.0.dist-info/top_level.txt
paizhaojieti_stdio_mcp-1.0.0.dist-info/RECORD
