Metadata-Version: 2.4
Name: paizhaojieti-stdio-mcp
Version: 1.0.0
Summary: 基于智谱AI拍照解题智能体的STDIO类型MCP服务
Home-page: https://github.com/La0bALanG/paizhaojieti_stdio_mcp
Author: Yutian
Author-email: Yutian <your.email@example.com>
License: MIT
Project-URL: Homepage, https://github.com/La0bALanG/paizhaojieti_stdio_mcp
Project-URL: Repository, https://github.com/La0bALanG/paizhaojieti_stdio_mcp
Project-URL: Issues, https://github.com/La0bALanG/paizhaojieti_stdio_mcp/issues
Keywords: mcp,stdio,ai,image-recognition,problem-solving
Classifier: Development Status :: 4 - Beta
Classifier: Intended Audience :: Developers
Classifier: Topic :: Software Development :: Libraries :: Python Modules
Classifier: License :: OSI Approved :: MIT License
Classifier: Programming Language :: Python :: 3
Classifier: Programming Language :: Python :: 3.7
Classifier: Programming Language :: Python :: 3.8
Classifier: Programming Language :: Python :: 3.9
Classifier: Programming Language :: Python :: 3.10
Classifier: Programming Language :: Python :: 3.11
Requires-Python: >=3.7
License-File: LICENSE
Requires-Dist: requests>=2.25.0
Dynamic: author
Dynamic: home-page
Dynamic: license-file
Dynamic: requires-python
